avocado_loader_yaml/__init__.py
tests/__init__.py
tests/test_yaml_loader.py
avocado_framework_plugin_loader_yaml-82.2.dist-info/METADATA
avocado_framework_plugin_loader_yaml-82.2.dist-info/WHEEL
avocado_framework_plugin_loader_yaml-82.2.dist-info/entry_points.txt
avocado_framework_plugin_loader_yaml-82.2.dist-info/top_level.txt
avocado_framework_plugin_loader_yaml-82.2.dist-info/RECORD
