Metadata-Version: 2.1
Name: avocado-framework-plugin-loader-yaml
Version: 82.2
Summary: Avocado Plugin that loads tests from YAML files
Home-page: http://avocado-framework.github.io/
Author: Avocado Developers
Author-email: avocado-devel@redhat.com
License: UNKNOWN
Platform: UNKNOWN
Requires-Dist: avocado-framework-plugin-varianter-yaml-to-mux (==82.2)
